[{"__type__":"cc.SpriteFrame","content":{"name":"result2","texture":"1dm/7H+gpKxa8TcklBZXjM","rect":[0,0,59,62],"offset":[0,0],"originalSize":[59,62],"capInsets":[0,0,0,0]}},{"__type__":"cc.SpriteFrame","content":{"name":"kwxresultbjt1","texture":"391EYMz1JCKri5HQ+F3HkJ","rect":[0,0,368,108],"offset":[0,0],"originalSize":[368,108],"capInsets":[0,0,0,0]}},{"__type__":"cc.SpriteFrame","content":{"name":"zmd_game_banker","texture":"d5IN/r3FtPwpmoSP7fO/dd","rect":[0,0,29,32],"offset":[0,0],"originalSize":[29,32],"capInsets":[0,0,0,0]}},[{"__type__":"cc.Prefab","_name":"itemresult1","data":{"__id__":1}},{"__type__":"cc.Node","_name":"itemresult1","_children":[{"__id__":2},{"__id__":13},{"__id__":14},{"__id__":16},{"__id__":18},{"__id__":23}],"_components":[{"__type__":"cc.Sprite","node":{"__id__":1},"_materials":[{"__uuid__":"ecpdLyjvZBwrvm+cedCcQy"}],"_spriteFrame":{"__uuid__":"e2Ydx88G1MUJi6VgpNzYeB"}},{"__type__":"60035blHzlCiaAKXPv1cfsn","node":{"__id__":1},"lab_name":{"__id__":15},"lab_tips":{"__id__":17},"lab_allscore":{"__id__":4},"lab_piao":{"__id__":6},"lab_gang":{"__id__":8},"lab_fan":{"__id__":10},"lab_ma":{"__id__":12},"node_icon":{"__id__":13},"KWXOutArea":{"__id__":22},"KWXCpgArea":{"__id__":20}}],"_prefab":{"__type__":"cc.PrefabInfo","root":{"__id__":1},"asset":{"__uuid__":"d1FCGyWzZFK7GNlERONxlz"},"fileId":"8dZ1nk/XFEerb9qw3FIy/E"},"_contentSize":{"__type__":"cc.Size","width":1204,"height":124},"_trs":{"__type__":"TypedArray","ctor":"Float64Array","array":[0,0,0,0,0,0,1,1,1,1]}},{"__type__":"cc.Node","_name":"scorebg","_parent":{"__id__":1},"_children":[{"__id__":3},{"__id__":5},{"__id__":7},{"__id__":9},{"__id__":11}],"_components":[{"__type__":"cc.Sprite","node":{"__id__":2},"_materials":[{"__uuid__":"ecpdLyjvZBwrvm+cedCcQy"}],"_spriteFrame":{"__uuid__":"70mnWeMVVGt4Jqf8ZL/sTz"}}],"_prefab":{"__type__":"cc.PrefabInfo","root":{"__id__":1},"asset":{"__uuid__":"d1FCGyWzZFK7GNlERONxlz"},"fileId":"b6uX5yKVZDlrroZGKhVORZ"},"_contentSize":{"__type__":"cc.Size","width":368,"height":108},"_trs":{"__type__":"TypedArray","ctor":"Float64Array","array":[408,0,0,0,0,0,1,1,1,1]}},{"__type__":"cc.Node","_name":"allscore","_parent":{"__id__":2},"_components":[{"__id__":4}],"_prefab":{"__type__":"cc.PrefabInfo","root":{"__id__":1},"asset":{"__uuid__":"d1FCGyWzZFK7GNlERONxlz"},"fileId":"8bTHUtXnRH6rUgx13ZWJTs"},"_color":{"__type__":"cc.Color","r":174,"g":144,"b":115},"_contentSize":{"__type__":"cc.Size","width":80.51,"height":26.46},"_anchorPoint":{"__type__":"cc.Vec2","y":0.5},"_trs":{"__type__":"TypedArray","ctor":"Float64Array","array":[-160,23,0,0,0,0,1,1,1,1]}},{"__type__":"cc.Label","node":{"__id__":3},"_materials":[{"__uuid__":"ecpdLyjvZBwrvm+cedCcQy"}],"_useOriginalSize":false,"_string":"总分： 9","_N$string":"总分： 9","_fontSize":21,"_lineHeight":21,"_N$horizontalAlign":1,"_N$verticalAlign":1},{"__type__":"cc.Node","_name":"piao","_parent":{"__id__":2},"_components":[{"__id__":6}],"_prefab":{"__type__":"cc.PrefabInfo","root":{"__id__":1},"asset":{"__uuid__":"d1FCGyWzZFK7GNlERONxlz"},"fileId":"ad/hj1FPtHcr+cVbPimH7t"},"_color":{"__type__":"cc.Color","r":174,"g":144,"b":115},"_contentSize":{"__type__":"cc.Size","width":59.51,"height":26.46},"_anchorPoint":{"__type__":"cc.Vec2","y":0.5},"_trs":{"__type__":"TypedArray","ctor":"Float64Array","array":[-160,-21,0,0,0,0,1,1,1,1]}},{"__type__":"cc.Label","node":{"__id__":5},"_materials":[{"__uuid__":"ecpdLyjvZBwrvm+cedCcQy"}],"_useOriginalSize":false,"_string":"飘： 9","_N$string":"飘： 9","_fontSize":21,"_lineHeight":21,"_N$horizontalAlign":1,"_N$verticalAlign":1},{"__type__":"cc.Node","_name":"gang","_parent":{"__id__":2},"_components":[{"__id__":8}],"_prefab":{"__type__":"cc.PrefabInfo","root":{"__id__":1},"asset":{"__uuid__":"d1FCGyWzZFK7GNlERONxlz"},"fileId":"3cRzlDszBGL4GofLFSJTuB"},"_color":{"__type__":"cc.Color","r":174,"g":144,"b":115},"_contentSize":{"__type__":"cc.Size","width":59.51,"height":26.46},"_anchorPoint":{"__type__":"cc.Vec2","y":0.5},"_trs":{"__type__":"TypedArray","ctor":"Float64Array","array":[-76,-21,0,0,0,0,1,1,1,1]}},{"__type__":"cc.Label","node":{"__id__":7},"_materials":[{"__uuid__":"ecpdLyjvZBwrvm+cedCcQy"}],"_useOriginalSize":false,"_string":"杠： 9","_N$string":"杠： 9","_fontSize":21,"_lineHeight":21,"_N$horizontalAlign":1,"_N$verticalAlign":1},{"__type__":"cc.Node","_name":"fan","_parent":{"__id__":2},"_components":[{"__id__":10}],"_prefab":{"__type__":"cc.PrefabInfo","root":{"__id__":1},"asset":{"__uuid__":"d1FCGyWzZFK7GNlERONxlz"},"fileId":"b1nmgPLftOf6OeqYYR1Al0"},"_color":{"__type__":"cc.Color","r":174,"g":144,"b":115},"_contentSize":{"__type__":"cc.Size","width":59.51,"height":26.46},"_anchorPoint":{"__type__":"cc.Vec2","y":0.5},"_trs":{"__type__":"TypedArray","ctor":"Float64Array","array":[7,-21,0,0,0,0,1,1,1,1]}},{"__type__":"cc.Label","node":{"__id__":9},"_materials":[{"__uuid__":"ecpdLyjvZBwrvm+cedCcQy"}],"_useOriginalSize":false,"_string":"番： 9","_N$string":"番： 9","_fontSize":21,"_lineHeight":21,"_N$horizontalAlign":1,"_N$verticalAlign":1},{"__type__":"cc.Node","_name":"ma","_parent":{"__id__":2},"_components":[{"__id__":12}],"_prefab":{"__type__":"cc.PrefabInfo","root":{"__id__":1},"asset":{"__uuid__":"d1FCGyWzZFK7GNlERONxlz"},"fileId":"7duhhBVSdE+rvKmw04wTDw"},"_color":{"__type__":"cc.Color","r":174,"g":144,"b":115},"_contentSize":{"__type__":"cc.Size","width":59.51,"height":26.46},"_anchorPoint":{"__type__":"cc.Vec2","y":0.5},"_trs":{"__type__":"TypedArray","ctor":"Float64Array","array":[91,-21,0,0,0,0,1,1,1,1]}},{"__type__":"cc.Label","node":{"__id__":11},"_materials":[{"__uuid__":"ecpdLyjvZBwrvm+cedCcQy"}],"_useOriginalSize":false,"_string":"马： 9","_N$string":"马： 9","_fontSize":21,"_lineHeight":21,"_N$horizontalAlign":1,"_N$verticalAlign":1},{"__type__":"cc.Node","_name":"resulticon","_parent":{"__id__":1},"_components":[{"__type__":"cc.Sprite","node":{"__id__":13},"_materials":[{"__uuid__":"ecpdLyjvZBwrvm+cedCcQy"}],"_spriteFrame":{"__uuid__":"49u/Vh5w5OVr1PKYZoaOg2"}}],"_prefab":{"__type__":"cc.PrefabInfo","root":{"__id__":1},"asset":{"__uuid__":"d1FCGyWzZFK7GNlERONxlz"},"fileId":"0a7parflxJVZMpCdoKrjb+"},"_contentSize":{"__type__":"cc.Size","width":59,"height":62},"_trs":{"__type__":"TypedArray","ctor":"Float64Array","array":[137,0,0,0,0,0,1,1,1,1]}},{"__type__":"cc.Node","_name":"name","_parent":{"__id__":1},"_components":[{"__id__":15}],"_prefab":{"__type__":"cc.PrefabInfo","root":{"__id__":1},"asset":{"__uuid__":"d1FCGyWzZFK7GNlERONxlz"},"fileId":"6dkp4GbgBBGo+bzDgout7C"},"_contentSize":{"__type__":"cc.Size","width":66,"height":27.72},"_anchorPoint":{"__type__":"cc.Vec2","y":0.5},"_trs":{"__type__":"TypedArray","ctor":"Float64Array","array":[-583,45.728,0,0,0,0,1,1,1,1]}},{"__type__":"cc.Label","node":{"__id__":14},"_materials":[{"__uuid__":"ecpdLyjvZBwrvm+cedCcQy"}],"_useOriginalSize":false,"_string":"啥玩意","_N$string":"啥玩意","_fontSize":22,"_lineHeight":22,"_N$horizontalAlign":1,"_N$verticalAlign":1},{"__type__":"cc.Node","_name":"tips","_parent":{"__id__":1},"_components":[{"__id__":17}],"_prefab":{"__type__":"cc.PrefabInfo","root":{"__id__":1},"asset":{"__uuid__":"d1FCGyWzZFK7GNlERONxlz"},"fileId":"e1FkRMD9NFuLelsr0ynTXi"},"_contentSize":{"__type__":"cc.Size","width":67.24,"height":27.72},"_anchorPoint":{"__type__":"cc.Vec2","y":0.5},"_trs":{"__type__":"TypedArray","ctor":"Float64Array","array":[-466,45.728,0,0,0,0,1,1,1,1]}},{"__type__":"cc.Label","node":{"__id__":16},"_materials":[{"__uuid__":"ecpdLyjvZBwrvm+cedCcQy"}],"_useOriginalSize":false,"_string":"亮牌x2","_N$string":"亮牌x2","_fontSize":22,"_lineHeight":22,"_N$horizontalAlign":1,"_N$verticalAlign":1},{"__type__":"cc.Node","_name":"New Node","_parent":{"__id__":1},"_children":[{"__id__":19},{"__id__":21}],"_components":[{"__type__":"cc.Layout","node":{"__id__":18},"_layoutSize":{"__type__":"cc.Size","width":130,"height":124},"_resize":1,"_N$layoutType":1,"_N$spacingX":30}],"_prefab":{"__type__":"cc.PrefabInfo","root":{"__id__":1},"asset":{"__uuid__":"d1FCGyWzZFK7GNlERONxlz"},"fileId":"e2esrSN/dPtaAg1YAxoGPK"},"_contentSize":{"__type__":"cc.Size","width":130,"height":124},"_anchorPoint":{"__type__":"cc.Vec2","y":0.5},"_trs":{"__type__":"TypedArray","ctor":"Float64Array","array":[-598.441,0,0,0,0,0,1,1,1,1]}},{"__type__":"cc.Node","_name":"peng_area","_parent":{"__id__":18},"_components":[{"__type__":"cc.Widget","node":{"__id__":19},"_alignFlags":8},{"__id__":20},{"__type__":"cc.Layout","node":{"__id__":19},"_layoutSize":{"__type__":"cc.Size","height":80},"_resize":1,"_N$layoutType":1,"_N$spacingX":8,"_N$affectedByScale":true}],"_prefab":{"__type__":"cc.PrefabInfo","root":{"__id__":1},"asset":{"__uuid__":"d1FCGyWzZFK7GNlERONxlz"},"fileId":"6f4JJcqNpPX4SbekNAjTKb"},"_contentSize":{"__type__":"cc.Size","height":80},"_anchorPoint":{"__type__":"cc.Vec2","y":0.5},"_trs":{"__type__":"TypedArray","ctor":"Float64Array","array":[0,-20,0,0,0,0,1,1,1,1]}},{"__type__":"dd8ffVDBXhC7bUtgmP3w+5H","node":{"__id__":19},"node_area":{"__id__":19},"mj_combo":{"__uuid__":"3fi/Ah7ghE2YktxewAsgx0"}},{"__type__":"cc.Node","_name":"out_area","_parent":{"__id__":18},"_components":[{"__id__":22}],"_prefab":{"__type__":"cc.PrefabInfo","root":{"__id__":1},"asset":{"__uuid__":"d1FCGyWzZFK7GNlERONxlz"},"fileId":"e63fTls2JIRK70GJf7ZHc/"},"_contentSize":{"__type__":"cc.Size","width":100,"height":80},"_anchorPoint":{"__type__":"cc.Vec2","y":0.5},"_trs":{"__type__":"TypedArray","ctor":"Float64Array","array":[30,0,0,0,0,0,1,1,1,1]}},{"__type__":"473dfVn3OdEr5TzB52H7+9j","node":{"__id__":21},"node_outArea":{"__id__":21},"mj_prefab":{"__uuid__":"f7Ld6tSj1OeK2QTxxrWD4O"},"startPos":{"__type__":"cc.Vec2","y":-20},"offset":{"__type__":"cc.Vec2","x":38},"increase":false,"lineNumArr":[14]},{"__type__":"cc.Node","_name":"banker","_parent":{"__id__":1},"_active":false,"_components":[{"__type__":"cc.Sprite","node":{"__id__":23},"_materials":[{"__uuid__":"ecpdLyjvZBwrvm+cedCcQy"}],"_spriteFrame":{"__uuid__":"a3tga0IU5JObeNOP7ko0r0"}}],"_prefab":{"__type__":"cc.PrefabInfo","root":{"__id__":1},"asset":{"__uuid__":"d1FCGyWzZFK7GNlERONxlz"},"fileId":"d0zHRXNRtHprA4zB3DYuxG"},"_contentSize":{"__type__":"cc.Size","width":29,"height":32},"_trs":{"__type__":"TypedArray","ctor":"Float64Array","array":[503.119,25.458,0,0,0,0,1,1,1,1]}}],{"__type__":"cc.SpriteFrame","content":{"name":"kwxresultbjt","texture":"c6HNVuan1Ey4jN+pQ4/pBL","rect":[0,0,1204,124],"offset":[0,0],"originalSize":[1204,124],"capInsets":[0,0,0,0]}}]